bem/__init__.py
bem/_base_client.py
bem/_client.py
bem/_compat.py
bem/_constants.py
bem/_exceptions.py
bem/_files.py
bem/_models.py
bem/_qs.py
bem/_resource.py
bem/_response.py
bem/_streaming.py
bem/_types.py
bem/_version.py
bem/py.typed
bem/_utils/__init__.py
bem/_utils/_logs.py
bem/_utils/_proxy.py
bem/_utils/_reflection.py
bem/_utils/_resources_proxy.py
bem/_utils/_streams.py
bem/_utils/_sync.py
bem/_utils/_transform.py
bem/_utils/_typing.py
bem/_utils/_utils.py
bem/lib/.keep
bem/resources/__init__.py
bem/resources/action_type_configs.py
bem/resources/actions.py
bem/resources/events.py
bem/resources/pipelines.py
bem/resources/subscriptions.py
bem/resources/tasks.py
bem/resources/transformations.py
bem/resources/webhook_secret.py
bem/types/__init__.py
bem/types/action_base.py
bem/types/action_correct_route_params.py
bem/types/action_create_base_param.py
bem/types/action_create_params.py
bem/types/action_list_params.py
bem/types/action_type.py
bem/types/action_type_config.py
bem/types/action_type_config_base.py
bem/types/action_type_config_base_param.py
bem/types/action_type_config_create_base_param.py
bem/types/action_type_config_create_params.py
bem/types/action_type_config_list_params.py
bem/types/action_type_config_list_response.py
bem/types/action_type_config_param.py
bem/types/action_type_config_update_params.py
bem/types/action_type_config_upsert_base_param.py
bem/types/any_type.py
bem/types/create_action_base_param.py
bem/types/email_action_base.py
bem/types/email_action_base_param.py
bem/types/event.py
bem/types/event_base.py
bem/types/event_list_params.py
bem/types/event_list_response.py
bem/types/get_actions_response.py
bem/types/input_type.py
bem/types/join_action_base.py
bem/types/join_action_base_param.py
bem/types/pipeline.py
bem/types/pipeline_create_params.py
bem/types/pipeline_list_params.py
bem/types/pipeline_list_response.py
bem/types/pipeline_retrieve_response.py
bem/types/pipeline_update_params.py
bem/types/route_action_base.py
bem_ai-2.0.1.dist-info/METADATA
bem_ai-2.0.1.dist-info/WHEEL
bem_ai-2.0.1.dist-info/licenses/LICENSE
bem_ai-2.0.1.dist-info/RECORD
